prefix_free_sorted_cowlist_set.py
prefix_free_sorted_cowlist_set-0.1.0a1.dist-info/licenses/LICENSE
prefix_free_sorted_cowlist_set-0.1.0a1.dist-info/METADATA
prefix_free_sorted_cowlist_set-0.1.0a1.dist-info/WHEEL
prefix_free_sorted_cowlist_set-0.1.0a1.dist-info/top_level.txt
prefix_free_sorted_cowlist_set-0.1.0a1.dist-info/RECORD
