Metadata-Version: 2.4
Name: prefix-free-sorted-cowlist-set
Version: 0.1.0a1
Summary: A Python implementation of a prefix-free, sorted set of COWList, backed by a trie data structure for efficient prefix checking and maintenance of sorted order.
Author-email: Jifeng Wu <jifengwu2k@gmail.com>
License-Expression: MIT
Project-URL: Homepage, https://github.com/jifengwu2k/prefix-free-sorted-cowlist-set
Project-URL: Bug Tracker, https://github.com/jifengwu2k/prefix-free-sorted-cowlist-set/issues
Classifier: Programming Language :: Python :: 2
Classifier: Programming Language :: Python :: 3
Classifier: Operating System :: OS Independent
Requires-Python: >=2
License-File: LICENSE
Requires-Dist: cowlist
Requires-Dist: put-back-iterator
Requires-Dist: sortedcontainers
Requires-Dist: typing; python_version < "3.5"
Dynamic: license-file
